maleo/soma/types/controllers/__init__.py
maleo/soma/types/controllers/message.py
maleo/soma/types/controllers/rest.py
maleo_soma_types_controllers-0.0.4.dist-info/licenses/LICENSE
maleo_soma_types_controllers-0.0.4.dist-info/METADATA
maleo_soma_types_controllers-0.0.4.dist-info/WHEEL
maleo_soma_types_controllers-0.0.4.dist-info/top_level.txt
maleo_soma_types_controllers-0.0.4.dist-info/RECORD
