Metadata-Version: 2.4
Name: maleo-soma-types-controllers
Version: 0.0.4
Summary: Soma controllers types package for MaleoSuite
Author-email: Agra Bima Yuda <agra@nexmedis.com>
License: Proprietary
Requires-Python: >=3.12
License-File: LICENSE
Requires-Dist: black>=25.1.0
Requires-Dist: cachetools>=5.5.2
Requires-Dist: certifi>=2025.8.3
Requires-Dist: cfgv>=3.4.0
Requires-Dist: charset-normalizer>=3.4.3
Requires-Dist: click>=8.2.1
Requires-Dist: distlib>=0.4.0
Requires-Dist: filelock>=3.19.1
Requires-Dist: google-api-core>=2.25.1
Requires-Dist: google-auth>=2.40.3
Requires-Dist: google-cloud-pubsub>=2.31.1
Requires-Dist: googleapis-common-protos>=1.70.0
Requires-Dist: grpc-google-iam-v1>=0.14.2
Requires-Dist: grpcio>=1.74.0
Requires-Dist: grpcio-status>=1.74.0
Requires-Dist: identify>=2.6.13
Requires-Dist: idna>=3.10
Requires-Dist: importlib_metadata>=8.7.0
Requires-Dist: mypy_extensions>=1.1.0
Requires-Dist: nodeenv>=1.9.1
Requires-Dist: opentelemetry-api>=1.36.0
Requires-Dist: opentelemetry-sdk>=1.36.0
Requires-Dist: opentelemetry-semantic-conventions>=0.57b0
Requires-Dist: packaging>=25.0
Requires-Dist: pathspec>=0.12.1
Requires-Dist: platformdirs>=4.4.0
Requires-Dist: pre_commit>=4.3.0
Requires-Dist: proto-plus>=1.26.1
Requires-Dist: protobuf>=6.32.0
Requires-Dist: pyasn1>=0.6.1
Requires-Dist: pyasn1_modules>=0.4.2
Requires-Dist: PyYAML>=6.0.2
Requires-Dist: requests>=2.32.5
Requires-Dist: rsa>=4.9.1
Requires-Dist: typing_extensions>=4.15.0
Requires-Dist: urllib3>=2.5.0
Requires-Dist: virtualenv>=20.34.0
Requires-Dist: zipp>=3.23.0
Dynamic: license-file
